{
    "colorPrimary": {
        "thw": "#FFFFFF",
        "feuerwehr": "#FFFFFF",
        "bundeswehr": "#FFFFFF",
        "katastrophenschutz": "#FFFFFF",
        "kommunal": "#FFFFFF",
        "polizei": "#FFFFFF",
        "zoll": "#FFFFFF",
        "command": "#FFFF00",
        "undefined": "#FFFFFF"
    },
    "colorSecondary": {
        "thw": "#003399",
        "feuerwehr": "#FF0000",
        "bundeswehr": "#996633",
        "katastrophenschutz": "#DF6711",
        "kommunal": "#E26E0E",
        "polizei": "#13A538",
        "zoll": "#13A538",
        "command": "#000000",
        "undefined": "#000000"
    },
    "colorStroke": {
        "thw": "#003399",
        "feuerwehr": "#FF0000",
        "bundeswehr": "#996633",
        "katastrophenschutz": "#DF6711",
        "kommunal": "#E26E0E",
        "polizei": "#13A538",
        "zoll": "#13A538",
        "command": "#000000",
        "undefined": "#000000"
    }
}